<?xml version="1.0"?>
<ruleset name="WordPressStandardOverride">
  <description>Overrides various WordPress Code Standards.</description>
  
  <rule ref="WordPress">
    <exclude name="Generic.WhiteSpace.DisallowSpaceIndent" />
  </rule>
    
  <rule ref="Generic.WhiteSpace.ScopeIndent">
    <properties>
      <property name="indent" value="2"/>
      <property name="tabIndent" value="false"/>
    </properties>
  </rule>
    
  <rule ref="Generic.WhiteSpace.DisallowTabIndent" />

  <rule ref="PEAR.Functions.FunctionCallSignature">
    <properties>
      <property name="indent" value="2"/>
    </properties>
  </rule>
</ruleset>